{"serialNumber":"urn:uuid:0e901d61-e53f-443e-a663-8a4ad8e0e489","metadata":{"timestamp":"2023-11-21T20:05:07"},"components":[{"type":"application","licenses":[{"license":{"name":"MIT"}}],"version":"1.2.0","name":"alwaysonline"},{"name":"chinadns-ng","type":"application","licenses":[{"license":{"name":"AGPL-3.0-only"}}],"version":"2023.10.28"},{"type":"application","licenses":[{"license":{"name":"Apache-2.0"}}],"version":"0.1.4","name":"go-stun"},{"name":"internet-detector","type":"application","version":"1.0"},{"name":"natmapt","type":"application","version":"20230820","licenses":[{"license":{"name":"MIT"}}]},{"type":"application","licenses":[{"license":{"name":"MIT"}}],"version":"20230820","name":"natmapt-client-script-deluge"},{"licenses":[{"license":{"name":"MIT"}}],"type":"application","version":"20230820","name":"natmapt-client-script-transmission"},{"name":"natmapt-notify-script-pushbullet","version":"20230820","type":"application","licenses":[{"license":{"name":"MIT"}}]},{"name":"natmapt-notify-script-pushover","version":"20230820","type":"application","licenses":[{"license":{"name":"MIT"}}]},{"version":"20230820","type":"application","licenses":[{"license":{"name":"MIT"}}],"name":"natmapt-notify-script-telegram"},{"name":"natter","type":"application","version":"0.9","licenses":[{"license":{"name":"GPL-3"}}]},{"name":"natter-ddns-script-cloudflare","type":"application","version":"0.9","licenses":[{"license":{"name":"GPL-3"}}]},{"name":"natter-notify-script-pushbullet","version":"0.9","type":"application","licenses":[{"license":{"name":"GPL-3"}}]},{"name":"natter-notify-script-telegram","type":"application","licenses":[{"license":{"name":"GPL-3"}}],"version":"0.9"},{"type":"application","version":"1.33.1","licenses":[{"license":{"name":"GPL-3.0-or-later"}}],"name":"netdata-ssl","cpe":"cpe:/a:my-netdata:netdata:1.33.1"},{"name":"pcap-dnsproxy","licenses":[{"license":{"name":"GPL-2.0"}}],"type":"application","version":"0.4.9.13-70a40bb"},{"version":"20230426","type":"application","licenses":[{"license":{"name":"MIT"}}],"name":"php-nginx"},{"name":"plain-nginx","version":"20231028","type":"application","licenses":[{"license":{"name":"MIT"}}]},{"type":"application","licenses":[{"license":{"name":"MIT"}}],"version":"1.4.7","name":"rgmac"},{"licenses":[{"license":{"name":"Apache-2.0"}}],"type":"application","version":"1.2.16","name":"stuntman-client"},{"name":"stuntman-server","type":"application","licenses":[{"license":{"name":"Apache-2.0"}}],"version":"1.2.16"},{"name":"stuntman-testcode","version":"1.2.16","type":"application","licenses":[{"license":{"name":"Apache-2.0"}}]},{"version":"0.4.0.2","type":"application","licenses":[{"license":{"name":"GPL-2.0"}}],"name":"Toolkit"},{"name":"uci-alwaysonline","type":"application","licenses":[{"license":{"name":"MIT"}}],"version":"1.2.0"},{"type":"application","licenses":[{"license":{"name":"MIT"}}],"version":"1.2.0","name":"uci-alwaysonline-nginx"}],"specVersion":"1.4","version":1,"bomFormat":"CycloneDX"}